setuptools_docker/Dockerfile.j2
setuptools_docker/__init__.py
setuptools_docker/command.py
setuptools_docker/docker-entrypoint.sh
setuptools_docker/docker.py
setuptools_docker-0.1.0.dist-info/LICENSE
setuptools_docker-0.1.0.dist-info/METADATA
setuptools_docker-0.1.0.dist-info/WHEEL
setuptools_docker-0.1.0.dist-info/entry_points.txt
setuptools_docker-0.1.0.dist-info/top_level.txt
setuptools_docker-0.1.0.dist-info/RECORD
