Metadata-Version: 2.1
Name: setuptools-docker
Version: 0.1.0
Summary: A setuptools extension for building docker images for distribution
Home-page: https://github.com/jcharlytown/setuptools-docker
Author: Julian Faude
Author-email: github@julianfau.de
License: Apache-2.0
Keywords: packaging,docker
Requires-Python: >=3.8
License-File: LICENSE
Requires-Dist: Jinja2
Requires-Dist: furl
Provides-Extra: tests
Requires-Dist: pytest ; extra == 'tests'
Requires-Dist: docker ; extra == 'tests'
Requires-Dist: requests ; extra == 'tests'
Requires-Dist: wheel ; extra == 'tests'
